semver_range.py
semver_range-0.0.3.dist-info/LICENSE.txt
semver_range-0.0.3.dist-info/METADATA
semver_range-0.0.3.dist-info/WHEEL
semver_range-0.0.3.dist-info/top_level.txt
semver_range-0.0.3.dist-info/RECORD
