Metadata-Version: 2.1
Name: semver-range
Version: 0.0.3
Summary: Python package that mimics npm’s “semver” package
Home-page: https://github.com/ushkarev/semver_range
Author: Igor Ushkarev
Author-email: UNKNOWN
License: MIT
Keywords: semver,semantic versioning,semantic version range,versioning,version
Platform: UNKNOWN
Classifier: Development Status :: 4 - Beta
Classifier: Intended Audience :: Developers
Classifier: License :: OSI Approved :: MIT License
Classifier: Natural Language :: English
Classifier: Operating System :: OS Independent
Classifier: Programming Language :: Python :: 3
Classifier: Programming Language :: Python :: 3.5
Classifier: Programming Language :: Python :: 3.6
Classifier: Programming Language :: Python :: 3.7
